{
  "scrapedAt": "2026-04-18T01:31:15.537Z",
  "topicsCount": 12,
  "topics": [
    {
      "title": "Opinions on Helium Browser?",
      "url": "https://www.reddit.com/r/privacy/comments/1so8aam/opinions_on_helium_browser/",
      "description": "<!-- SC_OFF --><div class=\"md\"><p>I’ve been using a lot of different browsers to find the best one for my needs and I came across Helium . On the surface it seems lightweight and focused, but I’m having trouble figuring out how it actually compares to more established privacy focused browsers like Brave. </p> </div><!-- SC_ON --> &#32; submitted by &#32; <a href=\" /u/Innovator-X </a> <br/> <span><",
      "pubDate": "2026-04-17T17:51:31.000Z",
      "source": "r/privacy",
      "redditScore": 0,
      "category": "Tech & Privacy",
      "score": 12,
      "sources": [
        "r/privacy"
      ],
      "content": "<!-- SC_OFF --><div class=\"md\"><p>I’ve been using a lot of different browsers to find the best one for my needs and I came across Helium . On the surface it seems lightweight and focused, but I’m having trouble figuring out how it actually compares to more established privacy focused browsers like Brave. </p> </div><!-- SC_ON --> &#32; submitted by &#32; <a href=\" /u/Innovator-X </a> <br/> <span><",
      "keywords": [
        "tech-&-privacy news",
        "helium",
        "browsers",
        "focused",
        "opinions",
        "browser",
        "been",
        "using"
      ],
      "hashtags": [
        "#tech-&-privacynews",
        "#helium",
        "#browsers",
        "#focused",
        "#opinions",
        "#browser",
        "#been",
        "#using"
      ],
      "slug": "2026-04-18-opinions-on-helium-browser",
      "sourceUrl": "https://www.reddit.com/r/privacy/comments/1so8aam/opinions_on_helium_browser/",
      "generatedAt": "2026-04-18T01:30:57.569Z",
      "relatedArticles": [
        {
          "title": "Opt-out banners, rejecting cookies, GPC signals all ignored by Google, Meta, and Microsoft. Google certified CMPs continuing to allow Google cookies to be set? Not suspicious at all",
          "slug": "2026-04-18-opt-out-banners-rejecting-cookies-gpc-signals-all-ignored-by-google-meta-and-mic",
          "category": "Tech & Privacy"
        },
        {
          "title": "The Parents decide act is Unconstitutional.",
          "slug": "2026-04-18-the-parents-decide-act-is-unconstitutional",
          "category": "Tech & Privacy"
        }
      ]
    },
    {
      "title": "Opt-out banners, rejecting cookies, GPC signals all ignored by Google, Meta, and Microsoft. Google certified CMPs continuing to allow Google cookies to be set? Not suspicious at all",
      "url": "https://www.reddit.com/r/privacy/comments/1snavvh/optout_banners_rejecting_cookies_gpc_signals_all/",
      "description": "<!-- SC_OFF --><div class=\"md\"><p>WebXray did an audit to see how compliant major sites and CMP managed sites are. Surprise surprise, they're not.</p> <p>100% of the tested CMPs continued to set cookies after receiving GCP or \"reject cookie\" signals. This is embarrassing for Google and, might I add, downright illegal.</p> <p>The best part is that Google 'certifies' these Consent Management Platfor",
      "pubDate": "2026-04-16T17:48:08.000Z",
      "source": "r/privacy",
      "redditScore": 0,
      "category": "Tech & Privacy",
      "score": 12,
      "sources": [
        "r/privacy"
      ],
      "content": "<!-- SC_OFF --><div class=\"md\"><p>WebXray did an audit to see how compliant major sites and CMP managed sites are. Surprise surprise, they're not.</p> <p>100% of the tested CMPs continued to set cookies after receiving GCP or \"reject cookie\" signals. This is embarrassing for Google and, might I add, downright illegal.</p> <p>The best part is that Google 'certifies' these Consent Management Platfor",
      "keywords": [
        "tech-&-privacy news",
        "google",
        "cookies",
        "signals",
        "cmps",
        "sites",
        "surprise",
        "banners"
      ],
      "hashtags": [
        "#tech-&-privacynews",
        "#google",
        "#cookies",
        "#signals",
        "#cmps",
        "#sites",
        "#surprise",
        "#banners"
      ],
      "slug": "2026-04-18-opt-out-banners-rejecting-cookies-gpc-signals-all-ignored-by-google-meta-and-mic",
      "sourceUrl": "https://www.reddit.com/r/privacy/comments/1snavvh/optout_banners_rejecting_cookies_gpc_signals_all/",
      "generatedAt": "2026-04-18T01:30:58.799Z",
      "relatedArticles": [
        {
          "title": "Opinions on Helium Browser?",
          "slug": "2026-04-18-opinions-on-helium-browser",
          "category": "Tech & Privacy"
        },
        {
          "title": "The Parents decide act is Unconstitutional.",
          "slug": "2026-04-18-the-parents-decide-act-is-unconstitutional",
          "category": "Tech & Privacy"
        }
      ]
    },
    {
      "title": "[FOIA] $10,000,000 Grant to AIDS Healthcare Foundation",
      "url": "https://www.muckrock.com/foi/united-states-of-america-10/10000000-grant-to-aids-healthcare-foundation-190233/",
      "description": "FOIA request to 80: $10,000,000 Grant to AIDS Healthcare Foundation. Status: processed.",
      "pubDate": "2026-04-18T01:30:51.594Z",
      "source": "MuckRock FOIA",
      "category": "Government Secrets",
      "score": 12,
      "sources": [
        "MuckRock FOIA"
      ],
      "content": "MuckRock users can file, duplicate, track, and share public records requests like this one. Learn more. Subject: Freedom of Information Act Request: $10,000,000 Grant to AIDS Healthcare Foundation Pursuant to the Freedom of Information Act, I hereby request the following records: All agreements with AIDS Healthcare Foundation (AHF) for any HUD funds or grants, including but not limited to the TEO grant for $10,000,000. All communications HUD had with ANYONE concerning or about the grant of TEO monies to AHF, whether the communication occurred before or after the grant of funds. This request includes but is not limited to, any HUD communications reconsidering or HUD’s decision to award $10,000,000 to AHF due to AHF’s actions as a landlord. The requested documents will be made available to the general public, and this request is not being made for commercial purposes. In the event that there are fees, I would be grateful if you would inform me of the total charges in advance of fulfilling my request. I would prefer the request filled electronically, by e-mail attachment if available or CD-ROM if not. Thank you in advance for your anticipated cooperation in this matter. I look forward to receiving your response to this request within 20 business days, as the statute requires. Subject: Status Update for Request #25-FI-HQ-03478 Dear Annette Harings, The status of your FOIA request #25-FI-HQ-03478 has been updated to the following status &#x27;Received&#x27;. To log into the HUD FOIA Public Access Website click on the Application URL below. Sincerely, U.S. Department of Housing and Urban Development Subject: Request Acknowledgement by U.S. Department of Housing and Urban Development Dear Annette Harings, Request number 25-FI-HQ-03478 has been assigned to the request you submitted via the HUD FOIA Public Access Website. In all future correspondence regarding this request please reference case number 25-FI-HQ-03478. Regards, U.S. Department of Housing and Urban Development Subject: Acknowledgement Letter for FOIA Request No. 25-FI-HQ-03478 Please review the attached Acknowledgement Letter. Thank you. Toyinka Taylor Government Information Specialist Acknowledgement Letter for FOIA 25-FI-HQ-03478 View Embed Opening and closing brackets with a diagonal slash through the middle. Embed Download An arrow pointing down Download Subject: RE: Freedom of Information Act Request #25-FI-HQ-03478 I wanted to follow up on the following Freedom of Information Act request, copied below, and originally submitted on July 27, 2025. Please let me know when I can expect to receive a response. You had assigned it reference number #25-FI-HQ-03478. Thanks for your help, and let me know if further clarification is needed.",
      "keywords": [
        "government-secrets news",
        "request",
        "foia",
        "grant",
        "subject",
        "information",
        "aids",
        "healthcare"
      ],
      "hashtags": [
        "#government-secretsnews",
        "#request",
        "#foia",
        "#grant",
        "#subject",
        "#information",
        "#aids",
        "#healthcare"
      ],
      "slug": "2026-04-18-foia-10000000-grant-to-aids-healthcare-foundation",
      "sourceUrl": "https://www.muckrock.com/foi/united-states-of-america-10/10000000-grant-to-aids-healthcare-foundation-190233/",
      "generatedAt": "2026-04-18T01:31:00.896Z",
      "relatedArticles": [
        {
          "title": "Internet Content Regulation is Coming To Canada",
          "slug": "2026-04-18-internet-content-regulation-is-coming-to-canada",
          "category": "Government Secrets"
        },
        {
          "title": "Go to your smart tv deepest settings, find all \"legitimate interest\" toggles buried in the deep details",
          "slug": "2026-04-18-go-to-your-smart-tv-deepest-settings-find-all-legitimate-interest-toggles-buried",
          "category": "Government Secrets"
        }
      ]
    },
    {
      "title": "The Parents decide act is Unconstitutional.",
      "url": "https://www.reddit.com/r/privacy/comments/1snghv5/the_parents_decide_act_is_unconstitutional/",
      "description": "<!-- SC_OFF --><div class=\"md\"><p>It requires sensitive information to be put in, needing that to just use a device is an invasion of privacy and a clear fourth amendment violation. Take a look, compromising people's privacy to \"protect kids\" is not a legal justification to nuke the fourth amendment. If you need to violate the fourth amendment to protect kids, maybe you're the problem.</p> <p><a h",
      "pubDate": "2026-04-16T21:07:40.000Z",
      "source": "r/privacy",
      "redditScore": 0,
      "category": "Tech & Privacy",
      "score": 11,
      "sources": [
        "r/privacy"
      ],
      "content": "<!-- SC_OFF --><div class=\"md\"><p>It requires sensitive information to be put in, needing that to just use a device is an invasion of privacy and a clear fourth amendment violation. Take a look, compromising people's privacy to \"protect kids\" is not a legal justification to nuke the fourth amendment. If you need to violate the fourth amendment to protect kids, maybe you're the problem.</p> <p><a h",
      "keywords": [
        "tech-&-privacy news",
        "fourth",
        "amendment",
        "privacy",
        "protect",
        "kids",
        "parents",
        "decide"
      ],
      "hashtags": [
        "#tech-&-privacynews",
        "#fourth",
        "#amendment",
        "#privacy",
        "#protect",
        "#kids",
        "#parents",
        "#decide"
      ],
      "slug": "2026-04-18-the-parents-decide-act-is-unconstitutional",
      "sourceUrl": "https://www.reddit.com/r/privacy/comments/1snghv5/the_parents_decide_act_is_unconstitutional/",
      "generatedAt": "2026-04-18T01:31:02.582Z",
      "relatedArticles": [
        {
          "title": "Opinions on Helium Browser?",
          "slug": "2026-04-18-opinions-on-helium-browser",
          "category": "Tech & Privacy"
        },
        {
          "title": "Opt-out banners, rejecting cookies, GPC signals all ignored by Google, Meta, and Microsoft. Google certified CMPs continuing to allow Google cookies to be set? Not suspicious at all",
          "slug": "2026-04-18-opt-out-banners-rejecting-cookies-gpc-signals-all-ignored-by-google-meta-and-mic",
          "category": "Tech & Privacy"
        }
      ]
    },
    {
      "title": "Uptick in security and off-topic posts. Please read the rules, this is not r/cybersecurity. We’re removing many more of these posts these days than ever before it seems.",
      "url": "https://www.reddit.com/r/privacy/comments/19flufu/uptick_in_security_and_offtopic_posts_please_read/",
      "description": "<!-- SC_OFF --><div class=\"md\"><p>Please read the rules, this is not <a href=\"/r/cybersecurity\">r/cybersecurity</a>. We’re removing many more of these posts these days than ever before it seems.</p> <h1>Tip: if you find yourself using the word “safe”, “secure”, “hacked”, etc in your title, you’re probably off-topic.</h1> </div><!-- SC_ON --> <br/> <span><a href=\" &#32; <span><a href=\"",
      "pubDate": "2024-01-25T22:34:37.000Z",
      "source": "r/privacy",
      "redditScore": 0,
      "category": "Corporate Watchdog",
      "score": 10,
      "sources": [
        "r/privacy",
        "r/conspiracy"
      ],
      "content": "<!-- SC_OFF --><div class=\"md\"><p>Please read the rules, this is not <a href=\"/r/cybersecurity\">r/cybersecurity</a>. We’re removing many more of these posts these days than ever before it seems.</p> <h1>Tip: if you find yourself using the word “safe”, “secure”, “hacked”, etc in your title, you’re probably off-topic.</h1> </div><!-- SC_ON --> <br/> <span><a href=\" &#32; <span><a href=\"",
      "keywords": [
        "corporate-watchdog news",
        "posts",
        "cybersecurity",
        "topic",
        "please",
        "read",
        "rules",
        "removing"
      ],
      "hashtags": [
        "#corporate-watchdognews",
        "#posts",
        "#cybersecurity",
        "#topic",
        "#please",
        "#read",
        "#rules",
        "#removing"
      ],
      "slug": "2026-04-18-uptick-in-security-and-off-topic-posts-please-read-the-rules-this-is-not-rcybers",
      "sourceUrl": "https://www.reddit.com/r/privacy/comments/19flufu/uptick_in_security_and_offtopic_posts_please_read/",
      "generatedAt": "2026-04-18T01:31:04.158Z",
      "relatedArticles": [
        {
          "title": "Convenience is slowly killing privacy, and most people don’t seem to care",
          "slug": "2026-04-18-convenience-is-slowly-killing-privacy-and-most-people-dont-seem-to-care",
          "category": "Corporate Watchdog"
        }
      ]
    },
    {
      "title": "Madison Square Garden's Surveillance Machine",
      "url": "https://www.wired.com/story/madison-square-garden-jim-dolan-surveillance-machine/",
      "description": "",
      "pubDate": "2026-04-18T00:59:13.000Z",
      "source": "Hacker News",
      "hnScore": 2,
      "hnComments": 4,
      "category": "Surveillance State",
      "score": 9,
      "sources": [
        "Hacker News",
        "r/technology"
      ],
      "content": "Loader Save Story Save this story Comment Loader Save Story Save this story I. “EXECUTIVE ONE” Her movements were tracked, over and over. When she sat down. When she ordered a drink. When she went to the bathroom. When she took the elevator. Nina Richards went to New York Knicks games quite a bit, and the security forces at Madison Square Garden used the arena&#x27;s network of cameras to follow her. New Yorkers have known for a long time that going to a game or concert at the Garden meant surrendering some privacy. That, as you watched the show, the Garden in a real sense watched you . Since 2018 , there have been reports of the venue deploying face-recognition technology in what critics believe are increasingly intrusive ways. Owner James Dolan has watch lists of basketball fans who have dared criticize his management. He keeps a close eye on his other venues too, including Radio City Music Hall and the Sphere in Las Vegas. Last March, Dolan’s security team blocked a graphic designer from seeing a concert; the designer, years earlier, had printed and sold a half-dozen T-shirts reading “ Ban Dolan .” He has locked out whole firms’ worth of lawyers, even keeping out a mom who was trying to take her 9-year-old Girl Scout to a Christmas show at Radio City Music Hall; the mom’s coworker had pissed him off. But the true extent of Dolan’s panopticon has only been caught in glimpses. A 2025 lawsuit by a former member of the MSG security team lifted the veil , just a bit. We started our own digging into the Garden&#x27;s operations. We discovered that Dolan’s security teams obsessively tracked Nina Richards, a trans woman, over a two-year period, monitoring her movements through the venue down to the second. (WIRED is using a pseudonym in this article out of respect for her privacy.) Dolan&#x27;s biometric surveillance is so extensive that a New York City police officer’s photo was added to a face-recognition database, and a child triggered an alert at one of Dolan’s properties. According to that lawsuit and our sources, Dolan’s head of corporate security takes such an expansive view of his mission that his employees will functionally cosplay as cops—patrolling the neighborhood, snooping on protesters if they happen to be in the area. You don&#x27;t have to enter a Dolan venue to be under his watch. The outside of Madison Square Garden in New York City. Photograph: Bruce Bennett/Getty Images For this story, we spoke with seven current and former employees of Dolan&#x27;s security service. We reviewed some of their confidential internal reports and Signal group chat messages. Behind the scenes, the atmosphere is so rooted in paranoia that former Knicks players warn one another about rooms being bugged, and staffers worry about being watched when they go out to local bars. “People are afraid, top to bottom. You can&#x27;t look at Mr. Dolan when he&#x27;s walking past. No, you can&#x27;t look at him,” one current member of the MSG security team says, adding that his bosses will sometimes say, “You&#x27;re too close to One—that&#x27;s what we call Mr. Dolan, ‘Executive One.’” James Dolan watches the Knicks play the Utah Jazz at Madison Square Garden. Photograph: Ron Antonelli/Getty Images MSG Entertainment declined to specifically comment on WIRED&#x27;s reporting about Dolan and the activities of his security teams. A company spokesperson said in a statement that “this story is built on false, misleading and unverified allegations, including claims drawn from lawsuits filed by rapacious litigators. We categorically reject such reckless reporting and are actively evaluating our legal options against WIRED.” There’s a long and well-documented history of controversy in pro sports’ executive suites. In just the past few years, NBA owners have been accused of being either an open racist, a sex pest, an alleged fraudster , or some combination. Dolan, who owns entertainment venues and sports teams, is at the vanguard of a different, and perhaps more disturbing, trend. Companies are now routinely collecting massive amounts of highly personal data on their customers, from their finger and palm prints to their faces. Executives across industries are enlisting private enforcers and former government intelligence operatives. All of which makes Dolan something of a pioneer, and a proof point. He’s showing that with enough money and motivation, any mogul can create his own deep state and build a sprawling surveillance enterprise with him in the middle. Graphic designer Frank Miller Jr. attempted to see a concert at Radio City Music Hall and received a trespass notice. Courtesy of Frank Miller Jr. II. “DO YOU KNOW WHO I AM?” Over the past few years, Jim Dolan has been on a high. His Knicks are a celebrity magnet and an on-court success. His Rangers are the second-most-valuable team in hockey, with a $4 billion valuation , according to Forbes. His Sphere is a Vegas must-see, a novel kind of high-tech, immersive entertainment. Dolan, at nearly 71 years old, serves as CEO and executive chairman of three public companies and is the chairman of a fourth. Their combined market cap of roughly $15 billion has more than doubled since 2022, according to one estimate, with Sphere Entertainment alone valued at more than $4 billion . Dolan has joined the upper ranks of media and tech moguls, with all that entails, from the corporate spooks to the MAGA connections. (Dolan&#x27;s Trump bona fides go further back than most; he got married at Mar-a-Lago in 2002.) But for decades, Dolan was seen as anything but a winner. He came into much of his empire from his father and was portrayed in New York media as a punch line: the thin-skinned, perpetually mad owner of a pair of hapless sports franchises; the nepo baby fumbling his dad’s largesse; the fedora-wearing frontman for a less-than-awesome Americana band. (One signature song : \"I Should’ve Known,\" about Dolan&#x27;s former friend Harvey Weinstein.) If Dolan was seen to have a strong suit in those days, it was generating fear. Multiple MSG executives have told reporters over the years that a \" culture of paranoia \" pervaded Jim Dolan&#x27;s Garden. As far back as 2001, staffers reportedly feared their phones had been bugged . Charles Dolan, left, with his son James Dolan in the control room of Cablevision Systems in Hauppauge, on Long Island in New York, on April 27, 1997. Photograph: VIC DE LUCIA/Redux The media became an early enemy. Dolan bragged that his PR department kept dossiers on journalists; other reporting showed that their conversations were monitored by Dolan’s minions. Adrian Wojnarowski, then the dean of the NBA press corps, was tailed inside the Garden, says one source with direct knowledge of the matter. (Wojnarowski declined to comment.) Another prominent basketball reporter shared with WIRED their concerns about connecting their phone to MSG&#x27;s Wi-Fi network; maybe the Garden&#x27;s staff could access the data inside. \"It&#x27;s the gulag\" is how one New York Post columnist described covering the Knicks in 2007. It could also be a clown show. While reporting on a story in 2013, one of us—Silverman—witnessed a Knick chowing down on a huge tub of popcorn in the locker room. Silverman was hustled off to the side by an MSG communications staffer, who promised that if this detail found its way into the piece, \"our relationship is over!\" while jabbing a finger into Silverman&#x27;s chest. Jim Dolan and Harvey Weinstein. Photograph: Theo Wargo/Getty Images Fans were next to face Dolan’s wrath. In 2014, a Wall Street trader was ejected from his Garden seat and ultimately arrested after shouting “You stink!” at Knicks star player Carmelo Anthony with 24 seconds left in the game. According to a court filing, MSG informed the trader’s employer that he&#x27;d been “belligerent” and used “offensive language,” and he lost his job . In 2017, a season-ticket holder said he told Dolan to sell the Knicks—and was tailed by security for several blocks. Even the team’s most famous fan, Spike Lee , claimed he was “ being harassed by James Dolan .” (In response, MSG said at the time that “the idea that Spike Lee is a victim … is laughable.”) MSG employees got the Dolan treatment too. In 2006, MSG marketing executive Anucha Browne Sanders accused the Knicks&#x27; then general manager, Isiah Thomas, of sexual discrimination—and, according to a complaint she filed, was fired in retaliation. A jury found the defendants, including MSG, liable for discrimination, and they eventually settled with Sanders, paying her more than $11 million . Close to a decade afterward, Dolan intimated that Browne Sanders was an opportunistic liar trying to squeeze MSG for a quick buck. Dolan was also known for lashing out at subordinates. Take the time in 2013 when an MSG security guard asked for his ID. “Do you know who I am?” he reportedly bellowed at the guard. “I’m your boss! I pay your salary!” (The guard was fired, then rehired the following day.) Anucha Browne Sanders leaves court on September 12, 2007. Photograph: Mariela Lombard/Reuters Some ex-MSG employees insist that Dolan can be genuinely considerate and giving at times. Vin Baker , a former Knick, credits Dolan as one of the few people who stood by him when he was struggling with alcoholism. Many of the Knicks’ biggest stars of years past now work for the team—or have become fixtures in the front row, come playoff time. Knicks legend and frequent Dolan critic Charles Oakley is not one of them. Oakley retired from the NBA in 2004 but continued to be an outsize presence in New York. For years, the famously combative Oakley says, he was followed both inside and outside MSG, where he’d watch his old team as a spectator. It all culminated in 2017 in a high-profile altercation in which he was hauled out of the Garden by a half dozen staffers mid-game, cuffed, and arrested. Dolan later implied Oakley might be a drunk. (Oakley sued several of Dolan’s companies, and while his defamation claim was dismissed, the court is still adjudicating the lawsuit&#x27;s two other counts.) It was hard not to see it as a warning to Dolan&#x27;s other perceived foes; if this can happen to a rough-and-tumble fan-favorite like Oak, it can happen to anyone. Former New York Knicks player Charles Oakley watches a game against the Toronto Raptors on March 20, 2012, at Madison Square Garden. Photograph: Nathaniel S. Butler/Getty Images By 2018, Dolan had a new security chief, John Eversole, and a new tool for making good on those warnings. Face-recognition technology had entered the Garden. A notice about face-recognition technology at Madison Square Garden. Photograph: Christina Horsten/Getty Images III. “THIS IS NOT OK” Soon after the Garden began to relax its Covid restrictions in the spring of 2021, Nina Richards was regularly going to Knicks games there. According to one former MSG security staffer, she became a fixation for Eversole. Eversole, a former senior director of global investigations at Oracle, instructed his deputies to compile “work-ups”—open source intelligence dossiers—on her. He made sure she was in the Garden&#x27;s face-recognition system and ordered the Garden&#x27;s security apparatus to focus on her, former MSG security staffer Donnie Ingrasselino later alleged in a lawsuit. Not because she posed any kind of danger at that moment. Because Richards was a transgender woman, and Eversole allegedly wanted to keep her “away from the players.” Eversole targeted Richards “because of her gender identity,” Ingrasselino added in his suit. Employees who were forced to conduct the surveillance were often uncomfortable, since they believed it to be a clear act of profiling, according to the first former staffer. \"She posed no threat,\" added a second former employee. \"She wasn&#x27;t taking pictures in restricted areas. She wasn&#x27;t trying to go places she shouldn&#x27;t be,” the source continued. “This is just a very large transgender woman, being a fan, walking around.” But Eversole&#x27;s orders were explicit: Keep watching. According to the lawsuit, he showed Richards&#x27; picture in several weekly meetings, misgendering her, and telling employees to watch out for “him or it or whatever it is.” Ingrasselino further contends in his court filing that “Eversole did not similarly limit access to others who socialized with athletes, including individuals who had extensive criminal histories and had the potential of posing a legitimate threat to MSG.” On January 10, 2022, the Knicks played the San Antonio Spurs at the Garden. It was Pride night . Richards was there, attending with a friend. An 18-page report prepared by Eversole&#x27;s Threat Management Group and reviewed by WIRED shows just how closely she was being monitored.",
      "keywords": [
        "surveillance-state news",
        "dolan",
        "garden",
        "security",
        "knicks",
        "former",
        "their",
        "york"
      ],
      "hashtags": [
        "#surveillance-statenews",
        "#dolan",
        "#garden",
        "#security",
        "#knicks",
        "#former",
        "#their",
        "#york"
      ],
      "slug": "2026-04-18-madison-square-gardens-surveillance-machine",
      "sourceUrl": "https://www.wired.com/story/madison-square-garden-jim-dolan-surveillance-machine/",
      "generatedAt": "2026-04-18T01:31:05.543Z",
      "relatedArticles": [
        {
          "title": "Handful of House Dems help extend surveillance powers until April 30 after late-night vote where some GOP revolted against it",
          "slug": "2026-04-18-handful-of-house-dems-help-extend-surveillance-powers-until-april-30-after-late",
          "category": "Surveillance State"
        }
      ]
    },
    {
      "title": "Handful of House Dems help extend surveillance powers until April 30 after late-night vote where some GOP revolted against it",
      "url": "https://www.reddit.com/r/privacy/comments/1snzvjs/handful_of_house_dems_help_extend_surveillance/",
      "description": "&#32; submitted by &#32; <a href=\" /u/1zzie </a> <br/> <span><a href=\" &#32; <span><a href=\"",
      "pubDate": "2026-04-17T12:43:10.000Z",
      "source": "r/privacy",
      "redditScore": 0,
      "category": "Surveillance State",
      "score": 9,
      "sources": [
        "r/privacy"
      ],
      "content": "&#32; submitted by &#32; <a href=\" /u/1zzie </a> <br/> <span><a href=\" &#32; <span><a href=\"",
      "keywords": [
        "surveillance-state news",
        "handful",
        "house",
        "dems",
        "help",
        "extend",
        "surveillance",
        "powers"
      ],
      "hashtags": [
        "#surveillance-statenews",
        "#handful",
        "#house",
        "#dems",
        "#help",
        "#extend",
        "#surveillance",
        "#powers"
      ],
      "slug": "2026-04-18-handful-of-house-dems-help-extend-surveillance-powers-until-april-30-after-late",
      "sourceUrl": "https://www.reddit.com/r/privacy/comments/1snzvjs/handful_of_house_dems_help_extend_surveillance/",
      "generatedAt": "2026-04-18T01:31:07.312Z",
      "relatedArticles": [
        {
          "title": "Madison Square Garden's Surveillance Machine",
          "slug": "2026-04-18-madison-square-gardens-surveillance-machine",
          "category": "Surveillance State"
        }
      ]
    },
    {
      "title": "Internet Content Regulation is Coming To Canada",
      "url": "https://www.reddit.com/r/privacy/comments/1so4zft/internet_content_regulation_is_coming_to_canada/",
      "description": "<!-- SC_OFF --><div class=\"md\"><p>Heritage Minister Marc Miller told reporters that the new majority government presents \"an opportunity\" to push through legislation that stalled out in the past.</p> </div><!-- SC_ON --> &#32; submitted by &#32; <a href=\" /u/stuntpope </a> <br/> <span><a href=\" &#32; <span><a href=\"",
      "pubDate": "2026-04-17T15:53:57.000Z",
      "source": "r/privacy",
      "redditScore": 0,
      "category": "Government Secrets",
      "score": 9,
      "sources": [
        "r/privacy"
      ],
      "content": "<!-- SC_OFF --><div class=\"md\"><p>Heritage Minister Marc Miller told reporters that the new majority government presents \"an opportunity\" to push through legislation that stalled out in the past.</p> </div><!-- SC_ON --> &#32; submitted by &#32; <a href=\" /u/stuntpope </a> <br/> <span><a href=\" &#32; <span><a href=\"",
      "keywords": [
        "government-secrets news",
        "internet",
        "content",
        "regulation",
        "coming",
        "canada",
        "heritage",
        "minister"
      ],
      "hashtags": [
        "#government-secretsnews",
        "#internet",
        "#content",
        "#regulation",
        "#coming",
        "#canada",
        "#heritage",
        "#minister"
      ],
      "slug": "2026-04-18-internet-content-regulation-is-coming-to-canada",
      "sourceUrl": "https://www.reddit.com/r/privacy/comments/1so4zft/internet_content_regulation_is_coming_to_canada/",
      "generatedAt": "2026-04-18T01:31:08.878Z",
      "relatedArticles": [
        {
          "title": "[FOIA] $10,000,000 Grant to AIDS Healthcare Foundation",
          "slug": "2026-04-18-foia-10000000-grant-to-aids-healthcare-foundation",
          "category": "Government Secrets"
        },
        {
          "title": "Go to your smart tv deepest settings, find all \"legitimate interest\" toggles buried in the deep details",
          "slug": "2026-04-18-go-to-your-smart-tv-deepest-settings-find-all-legitimate-interest-toggles-buried",
          "category": "Government Secrets"
        }
      ]
    },
    {
      "title": "Convenience is slowly killing privacy, and most people don’t seem to care",
      "url": "https://www.reddit.com/r/privacy/comments/1sns7cl/convenience_is_slowly_killing_privacy_and_most/",
      "description": "<!-- SC_OFF --><div class=\"md\"><p>Every time a service asks for more data, it’s framed as “making things easier” or “improving security.”</p> <p>And most of us just accept it without thinking twice.</p> <p>But at what point do we realize we’ve traded away too much?</p> <p>Do people actually care about privacy anymore, or only after something goes wrong?</p> </div><!-- SC_ON --> &#32; submitted by ",
      "pubDate": "2026-04-17T05:52:44.000Z",
      "source": "r/privacy",
      "redditScore": 0,
      "category": "Corporate Watchdog",
      "score": 9,
      "sources": [
        "r/privacy"
      ],
      "content": "<!-- SC_OFF --><div class=\"md\"><p>Every time a service asks for more data, it’s framed as “making things easier” or “improving security.”</p> <p>And most of us just accept it without thinking twice.</p> <p>But at what point do we realize we’ve traded away too much?</p> <p>Do people actually care about privacy anymore, or only after something goes wrong?</p> </div><!-- SC_ON --> &#32; submitted by ",
      "keywords": [
        "corporate-watchdog news",
        "privacy",
        "people",
        "care",
        "convenience",
        "slowly",
        "killing",
        "seem"
      ],
      "hashtags": [
        "#corporate-watchdognews",
        "#privacy",
        "#people",
        "#care",
        "#convenience",
        "#slowly",
        "#killing",
        "#seem"
      ],
      "slug": "2026-04-18-convenience-is-slowly-killing-privacy-and-most-people-dont-seem-to-care",
      "sourceUrl": "https://www.reddit.com/r/privacy/comments/1sns7cl/convenience_is_slowly_killing_privacy_and_most/",
      "generatedAt": "2026-04-18T01:31:10.655Z",
      "relatedArticles": [
        {
          "title": "Uptick in security and off-topic posts. Please read the rules, this is not r/cybersecurity. We’re removing many more of these posts these days than ever before it seems.",
          "slug": "2026-04-18-uptick-in-security-and-off-topic-posts-please-read-the-rules-this-is-not-rcybers",
          "category": "Corporate Watchdog"
        }
      ]
    },
    {
      "title": "Google Chrome lacks protection against one of the most basic and common ways to track users online (Browser fingerprinting is everywhere)",
      "url": "https://www.reddit.com/r/privacy/comments/1so2gvs/google_chrome_lacks_protection_against_one_of_the/",
      "description": "<!-- SC_OFF --><div class=\"md\"><p>Article in <strong>The Register</strong>:</p> <p><a href=\" <blockquote> <p>Google markets its Chrome browser by citing its superior safety features, but according to privacy consultant Alexander Hanff, Chrome does not protect against browser fingerprinting – a method of tracking people online by capturing technical details about their browser.</p> </blockquote> <p",
      "pubDate": "2026-04-17T14:23:05.000Z",
      "source": "r/privacy",
      "redditScore": 0,
      "category": "Tech & Privacy",
      "score": 9,
      "sources": [
        "r/privacy"
      ],
      "content": "<!-- SC_OFF --><div class=\"md\"><p>Article in <strong>The Register</strong>:</p> <p><a href=\" <blockquote> <p>Google markets its Chrome browser by citing its superior safety features, but according to privacy consultant Alexander Hanff, Chrome does not protect against browser fingerprinting – a method of tracking people online by capturing technical details about their browser.</p> </blockquote> <p",
      "keywords": [
        "tech-&-privacy news",
        "browser",
        "chrome",
        "google",
        "against",
        "online",
        "fingerprinting",
        "blockquote"
      ],
      "hashtags": [
        "#tech-&-privacynews",
        "#browser",
        "#chrome",
        "#google",
        "#against",
        "#online",
        "#fingerprinting",
        "#blockquote"
      ],
      "slug": "2026-04-18-google-chrome-lacks-protection-against-one-of-the-most-basic-and-common-ways-to",
      "sourceUrl": "https://www.reddit.com/r/privacy/comments/1so2gvs/google_chrome_lacks_protection_against_one_of_the/",
      "generatedAt": "2026-04-18T01:31:12.039Z",
      "relatedArticles": [
        {
          "title": "Opinions on Helium Browser?",
          "slug": "2026-04-18-opinions-on-helium-browser",
          "category": "Tech & Privacy"
        },
        {
          "title": "Opt-out banners, rejecting cookies, GPC signals all ignored by Google, Meta, and Microsoft. Google certified CMPs continuing to allow Google cookies to be set? Not suspicious at all",
          "slug": "2026-04-18-opt-out-banners-rejecting-cookies-gpc-signals-all-ignored-by-google-meta-and-mic",
          "category": "Tech & Privacy"
        }
      ]
    },
    {
      "title": "Go to your smart tv deepest settings, find all \"legitimate interest\" toggles buried in the deep details",
      "url": "https://www.reddit.com/r/privacy/comments/1so3tn4/go_to_your_smart_tv_deepest_settings_find_all/",
      "description": "<!-- SC_OFF --><div class=\"md\"><p>As per title, go to your smart tv deepest settings, find all \"legitimate interest\" toggles buried in the deep details and untick hundreds of them manually one by one. Yes, it will take you 45 minutes but it has to be done. </p> </div><!-- SC_ON --> &#32; submitted by &#32; <a href=\" /u/J-96788-EU </a> <br/> <span><a href=\" &#32; <span><a href=\"",
      "pubDate": "2026-04-17T15:12:09.000Z",
      "source": "r/privacy",
      "redditScore": 0,
      "category": "Government Secrets",
      "score": 9,
      "sources": [
        "r/privacy"
      ],
      "content": "<!-- SC_OFF --><div class=\"md\"><p>As per title, go to your smart tv deepest settings, find all \"legitimate interest\" toggles buried in the deep details and untick hundreds of them manually one by one. Yes, it will take you 45 minutes but it has to be done. </p> </div><!-- SC_ON --> &#32; submitted by &#32; <a href=\" /u/J-96788-EU </a> <br/> <span><a href=\" &#32; <span><a href=\"",
      "keywords": [
        "government-secrets news",
        "your",
        "smart",
        "deepest",
        "settings",
        "find",
        "legitimate",
        "interest"
      ],
      "hashtags": [
        "#government-secretsnews",
        "#your",
        "#smart",
        "#deepest",
        "#settings",
        "#find",
        "#legitimate",
        "#interest"
      ],
      "slug": "2026-04-18-go-to-your-smart-tv-deepest-settings-find-all-legitimate-interest-toggles-buried",
      "sourceUrl": "https://www.reddit.com/r/privacy/comments/1so3tn4/go_to_your_smart_tv_deepest_settings_find_all/",
      "generatedAt": "2026-04-18T01:31:13.437Z",
      "relatedArticles": [
        {
          "title": "[FOIA] $10,000,000 Grant to AIDS Healthcare Foundation",
          "slug": "2026-04-18-foia-10000000-grant-to-aids-healthcare-foundation",
          "category": "Government Secrets"
        },
        {
          "title": "Internet Content Regulation is Coming To Canada",
          "slug": "2026-04-18-internet-content-regulation-is-coming-to-canada",
          "category": "Government Secrets"
        }
      ]
    },
    {
      "title": "Need advice: system overhaul + data archiving",
      "url": "https://www.reddit.com/r/privacy/comments/1sogcgm/need_advice_system_overhaul_data_archiving/",
      "description": "<!-- SC_OFF --><div class=\"md\"><p>I've fallen off a bit with my privacy practices for various reasons. Right now I'm in the process of making the switch to linux on my main system. I plan on using pop_os as my main driver and then having a temporary dual boot of windows so I can run VR until I figure out how to get my quest 2 to talk to linux systems. After that I want to have backup distro thats ",
      "pubDate": "2026-04-17T22:54:10.000Z",
      "source": "r/privacy",
      "redditScore": 0,
      "category": "Tech & Privacy",
      "score": 9,
      "sources": [
        "r/privacy"
      ],
      "content": "<!-- SC_OFF --><div class=\"md\"><p>I've fallen off a bit with my privacy practices for various reasons. Right now I'm in the process of making the switch to linux on my main system. I plan on using pop_os as my main driver and then having a temporary dual boot of windows so I can run VR until I figure out how to get my quest 2 to talk to linux systems. After that I want to have backup distro thats ",
      "keywords": [
        "tech-&-privacy news",
        "system",
        "linux",
        "main",
        "need",
        "advice",
        "overhaul",
        "data"
      ],
      "hashtags": [
        "#tech-&-privacynews",
        "#system",
        "#linux",
        "#main",
        "#need",
        "#advice",
        "#overhaul",
        "#data"
      ],
      "slug": "2026-04-18-need-advice-system-overhaul-data-archiving",
      "sourceUrl": "https://www.reddit.com/r/privacy/comments/1sogcgm/need_advice_system_overhaul_data_archiving/",
      "generatedAt": "2026-04-18T01:31:14.513Z",
      "relatedArticles": [
        {
          "title": "Opinions on Helium Browser?",
          "slug": "2026-04-18-opinions-on-helium-browser",
          "category": "Tech & Privacy"
        },
        {
          "title": "Opt-out banners, rejecting cookies, GPC signals all ignored by Google, Meta, and Microsoft. Google certified CMPs continuing to allow Google cookies to be set? Not suspicious at all",
          "slug": "2026-04-18-opt-out-banners-rejecting-cookies-gpc-signals-all-ignored-by-google-meta-and-mic",
          "category": "Tech & Privacy"
        }
      ]
    }
  ]
}